circbuf-0.1b1.dist-info/DESCRIPTION.rst
circbuf-0.1b1.dist-info/WHEEL
circbuf-0.1b1.dist-info/metadata.json
circbuf-0.1b1.dist-info/METADATA
circbuf-0.1b1.dist-info/RECORD
circbuf-0.1b1.dist-info/top_level.txt
circbuf-0.1b1.data/data/tox.ini/tox.ini
circbuf/__init__.py
