Metadata-Version: 2.0
Name: circbuf
Version: 0.1b1
Summary: A fast, zero-copy, circular buffer for Python
Home-page: https://github.com/peteut/circbuf
Author: Alain Péteut
Author-email: alain.peteut@yahoo.com
License: MIT
Platform: all
Classifier: Development Status :: 4 - Beta
Classifier: Intended Audience :: Developers
Classifier: License :: OSI Approved :: MIT License
Classifier: Operating System :: OS Independent
Classifier: Programming Language :: Python :: 3
Classifier: Programming Language :: Python :: 3.2
Classifier: Programming Language :: Python :: 3.3
Classifier: Programming Language :: Python :: 3.4
